soundfile.py
_soundfile_data/COPYING
_soundfile_data/libsndfile32bit.dll
PySoundFile-0.9.0.post1.dist-info/DESCRIPTION.rst
PySoundFile-0.9.0.post1.dist-info/METADATA
PySoundFile-0.9.0.post1.dist-info/metadata.json
PySoundFile-0.9.0.post1.dist-info/RECORD
PySoundFile-0.9.0.post1.dist-info/top_level.txt
PySoundFile-0.9.0.post1.dist-info/WHEEL
