Metadata-Version: 1.1
Name: PySoundFile
Version: 0.9.0.post1
Summary: An audio library based on libsndfile, CFFI and NumPy
Home-page: https://github.com/bastibe/PySoundFile
Author: Bastian Bechtold
Author-email: basti@bastibe.de
License: BSD 3-Clause License
Keywords: audio,libsndfile
Platform: any
Classifier: Development Status :: 5 - Production/Stable
Classifier: Intended Audience :: Developers
Classifier: Intended Audience :: Science/Research
Classifier: License :: OSI Approved :: BSD License
Classifier: Natural Language :: English
Classifier: Operating System :: OS Independent
Classifier: Programming Language :: Python
Classifier: Programming Language :: Python :: 3
Classifier: Programming Language :: Python :: 2
Classifier: Programming Language :: Python :: Implementation :: PyPy
Classifier: Programming Language :: Python :: Implementation :: CPython
Classifier: Topic :: Multimedia :: Sound/Audio
